spatialmath/DualQuaternion.py
spatialmath/__init__.py
spatialmath/baseposelist.py
spatialmath/baseposematrix.py
spatialmath/geom2d.py
spatialmath/geom3d.py
spatialmath/pose2d.py
spatialmath/pose3d.py
spatialmath/quaternion.py
spatialmath/spatialvector.py
spatialmath/spline.py
spatialmath/timing.py
spatialmath/twist.py
spatialmath/base/__init__.py
spatialmath/base/_types_311.py
spatialmath/base/_types_35.py
spatialmath/base/_types_39.py
spatialmath/base/animate.py
spatialmath/base/argcheck.py
spatialmath/base/graphics.py
spatialmath/base/numeric.py
spatialmath/base/quaternions.py
spatialmath/base/symbolic.py
spatialmath/base/transforms2d.py
spatialmath/base/transforms3d.py
spatialmath/base/transformsNd.py
spatialmath/base/types.py
spatialmath/base/vectors.py
spatialmath_python_abarryfix-1.1.13.dist-info/LICENSE
spatialmath_python_abarryfix-1.1.13.dist-info/METADATA
spatialmath_python_abarryfix-1.1.13.dist-info/WHEEL
spatialmath_python_abarryfix-1.1.13.dist-info/top_level.txt
spatialmath_python_abarryfix-1.1.13.dist-info/RECORD
